frc1678/__init__.py
frc1678/limeplotter/__init__.py
frc1678/limeplotter/loaderbase.py
frc1678/limeplotter/logloader.py
frc1678/limeplotter/main.py
frc1678/limeplotter/networktablesloader.py
frc1678/limeplotter/networktablesserver.py
frc1678/limeplotter/loader/__init__.py
frc1678/limeplotter/loader/log.py
frc1678/limeplotter/loader/networktables.py
frc1678/limeplotter/loader/svg.py
frc1678/limeplotter/loader/timermarks.py
frc1678/limeplotter/loader/svgs/2019map.svg
frc1678/limeplotter/loader/svgs/2020map-full.svg
frc1678/limeplotter/loader/svgs/2020map-rev.svg
frc1678/limeplotter/loader/svgs/2020map.svg
frc1678/limeplotter/loader/svgs/2021.svg
frc1678/limeplotter/loader/svgs/2022.svg
frc1678_lime_plotter-0.6.8.dist-info/METADATA
frc1678_lime_plotter-0.6.8.dist-info/WHEEL
frc1678_lime_plotter-0.6.8.dist-info/entry_points.txt
frc1678_lime_plotter-0.6.8.dist-info/top_level.txt
frc1678_lime_plotter-0.6.8.dist-info/RECORD
