Metadata-Version: 2.1
Name: frc1678-lime-plotter
Version: 0.6.8
Summary: A matplotlib based plotter for FRC logs and networktables
Home-page: https://github.com/frc1678/lime-plotter
Author: Wes Hardaker
Author-email: opensource@hardakers.net
License: UNKNOWN
Platform: UNKNOWN
Classifier: Programming Language :: Python :: 3
Classifier: Operating System :: OS Independent
Requires-Python: >=3
Requires-Dist: pynetworktables
Requires-Dist: numpy
Requires-Dist: pandas
Requires-Dist: pyyaml
Requires-Dist: matplotlib
Requires-Dist: svgpath2mpl
